.DS_Store
xrotor/__init__.py
xrotor/libxrotor.dylib
xrotor/model.py
xrotor/test.py
xrotor/xrotor.py
xrotor-1.3.1.dist-info/LICENSE.txt
xrotor-1.3.1.dist-info/METADATA
xrotor-1.3.1.dist-info/WHEEL
xrotor-1.3.1.dist-info/top_level.txt
xrotor-1.3.1.dist-info/RECORD
